__init__.py
lib_sudoku-2.2.0.dist-info/METADATA
lib_sudoku-2.2.0.dist-info/WHEEL
lib_sudoku-2.2.0.dist-info/licenses/LICENSE
lib_sudoku.pyi
lib_sudoku/__init__.py
lib_sudoku/__init__.pyi
lib_sudoku/lib_sudoku.cpython-311-darwin.so
lib_sudoku/py.typed
lib_sudoku-2.2.0.dist-info/RECORD
