Metadata-Version: 2.4
Name: lib_sudoku
Version: 2.2.0
License-File: LICENSE
Summary: A blazing fast sudoku library buit in rust
Requires-Python: >=3.8
Project-URL: Homepage, https://github.com/shaggysa/lib_sudoku
Project-URL: Source Code, https://github.com/shaggysa/lib_sudoku
Project-URL: Issues, https://github.com/shaggysa/lib_sudoku/issues
